markdown_to_json/__init__.py
markdown_to_json/__main__.py
markdown_to_json/_metadata.py
markdown_to_json/markdown_to_json.py
markdown_to_json/scripts/__init__.py
markdown_to_json/scripts/md_to_json.py
markdown_to_json/vendor/CommonMark/CommonMark.py
markdown_to_json/vendor/CommonMark/LICENSE
markdown_to_json/vendor/CommonMark/README.md
markdown_to_json/vendor/CommonMark/__init__.py
markdown_to_json/vendor/CommonMark/entitytrans.py
markdown_to_json/vendor/CommonMark/test/test-CommonMark.py
markdown_to_json/vendor/__init__.py
markdown_to_json/vendor/docopt/LICENSE-MIT
markdown_to_json/vendor/docopt/__init__.py
markdown_to_json/vendor/docopt/_version.py
markdown_to_json/vendor/docopt/py.typed
markdown_to_json-2.1.2.dist-info/LICENSE
markdown_to_json-2.1.2.dist-info/METADATA
markdown_to_json-2.1.2.dist-info/WHEEL
markdown_to_json-2.1.2.dist-info/entry_points.txt
markdown_to_json-2.1.2.dist-info/RECORD
