Metadata-Version: 2.1
Name: markdown_to_json
Version: 2.1.2
Summary: Markdown to dict and json deserializer
Home-page: https://github.com/njvack/markdown-to-json
License: MIT
Keywords: serializer,deserializer,markdown
Author: Nathan Vack
Author-email: njvack@wisc.edu
Requires-Python: >=3.8
Classifier: Development Status :: 3 - Alpha
Classifier: Intended Audience :: Developers
Classifier: License :: OSI Approved :: MIT License
Classifier: Operating System :: OS Independent
Classifier: Programming Language :: Python
Classifier: Programming Language :: Python :: 3
Classifier: Programming Language :: Python :: 3.8
Classifier: Programming Language :: Python :: 3.9
Classifier: Programming Language :: Python :: 3.10
Classifier: Programming Language :: Python :: 3.11
Classifier: Programming Language :: Python :: 3.12
Project-URL: Bug Tracker, https://github.com/njvack/markdown-to-json/issues
Project-URL: Change Log, https://github.com/njvack/markdown-to-json/blob/main/CHANGELOG.md
Project-URL: Documentation, https://github.com/njvack/markdown-to-json
Project-URL: Repository, https://github.com/njvack/markdown-to-json
